{
  "data": [
    {
      "eventName": "Happy Hour1",
      "lat": 39.958111,
      "lng": -86.013588,
      "date": "2022-08-31T02:15:12.356Z"
    },
    {
      "eventName": "Crazy concert",
      "lat": 40.001572,
      "lng": -85.935173,
      "date": "2022-10-31T02:15:12.356Z"
    },
    {
      "eventName": "Fireworks",
      "lat": 39.770569,
      "lng": -86.155319,
      "date": "2022-07-04T02:15:12.356Z"
    },
    {
      "eventName": "GenCon",
      "lat": 39.769249,
      "lng": -86.162552,
      "date": "2022-06-19T02:15:12.356Z"
    },
    {
      "eventName": "Christmas Market",
      "lat": 39.97402,
      "lng": -86.12566,
      "date": "2022-01-01T02:15:12.356Z"
    }
  ]
}
